volexity/goresolver/__init__.py
volexity/goresolver/_version.py
volexity/goresolver/cli.py
volexity/goresolver/go_compare.py
volexity/goresolver/py.typed
volexity/goresolver/buildinfo/__init__.py
volexity/goresolver/buildinfo/go_buildinfo_parser.py
volexity/goresolver/models/__init__.py
volexity/goresolver/models/cli_arguments.py
volexity/goresolver/models/go_version.py
volexity/goresolver/models/symbol_report.py
volexity/goresolver/models/symbol_source.py
volexity/goresolver/models/symbol_tree.py
volexity/goresolver/sym/__init__.py
volexity/goresolver/sym/arch.py
volexity/goresolver/sym/binary.py
volexity/goresolver/sym/binary_reader.py
volexity/goresolver/sym/cstr.py
volexity/goresolver/sym/endian.py
volexity/goresolver/sym/func.py
volexity/goresolver/sym/go_sym_parser.py
volexity/goresolver/sym/go_type_parser.py
volexity/goresolver/sym/pc_line_magic.py
volexity/goresolver/sym/pc_line_table.py
volexity/goresolver/sym/signature.py
volexity/goresolver/sym/slice.py
volexity/goresolver/sym/type_flags.py
volexity/goresolver/sym/type_kinds.py
volexity/goresolver/sym/module_data_models/__init__.py
volexity/goresolver/sym/module_data_models/module_data.py
volexity/goresolver/sym/module_data_models/module_data_1_02.py
volexity/goresolver/sym/module_data_models/module_data_1_16.py
volexity/goresolver/sym/module_data_models/module_data_1_18.py
volexity/goresolver/sym/module_data_models/module_data_1_20.py
goresolver-1.4.1.dist-info/METADATA
goresolver-1.4.1.dist-info/WHEEL
goresolver-1.4.1.dist-info/entry_points.txt
goresolver-1.4.1.dist-info/licenses/LICENSE.md
goresolver-1.4.1.dist-info/RECORD
