Metadata-Version: 2.4
Name: goresolver
Version: 1.4.1
Summary: A tool generating and comparing control flow graphs of GO samples.
Project-URL: Documentation, https://gitlab.research.volexity.com/threat-intel/gographer/-/blob/master/README.md
Project-URL: Issues, https://gitlab.research.volexity.com/threat-intel/gographer/-/issues
Project-URL: Source, https://gitlab.research.volexity.com/threat-intel/gographer
Author-email: Killian Raimbaud <kraimbaud@volexity.com>
License-File: LICENSE.md
Classifier: Development Status :: 4 - Beta
Classifier: License :: Other/Proprietary License
Classifier: Programming Language :: Python
Classifier: Programming Language :: Python :: 3.12
Classifier: Programming Language :: Python :: 3.13
Classifier: Programming Language :: Python :: Implementation :: CPython
Classifier: Programming Language :: Python :: Implementation :: PyPy
Requires-Python: >=3.12
Requires-Dist: gographer~=1.2.2
Requires-Dist: gostrap~=1.1.2
Requires-Dist: lief~=0.16.4
Requires-Dist: multiprocess~=0.70.18
Requires-Dist: pygments~=2.18.0
Requires-Dist: yara-python~=4.5.1
